{
  "generated_at": "2026-05-31T13:49:50.572130Z",
  "window_hours": 24,
  "total_items": 31,
  "total_items_ai_raw": 31,
  "total_items_raw": 52,
  "total_items_all_mode": 52,
  "topic_filter": "ai_relevance_scoring_v0_4",
  "ai_relevance_threshold": 0.65,
  "archive_total": 808,
  "site_count": 1,
  "source_count": 2,
  "site_stats": [
    {
      "site_id": "opmlrss",
      "site_name": "OPML RSS",
      "count": 31,
      "raw_count": 52
    }
  ],
  "items": [
    {
      "id": "d00109d4c89faa4b99109ecfcf1739cb8fbdc65c",
      "site_id": "opmlrss",
      "site_name": "OPML RSS",
      "source": "36氪 - AI",
      "title": "思林杰：股东拟合计减持不超6%股份",
      "url": "https://36kr.com/newsflashes/3832895152187009?f=rss",
      "published_at": "2026-05-31T09:47:29Z",
      "first_seen_at": "2026-05-31T11:41:54.440430Z",
      "last_seen_at": "2026-05-31T13:49:50.572130Z",
      "ai_is_related": true,
      "ai_score": 0.67,
      "ai_label": "ai_general",
      "ai_relevance_reason": "matched_ai_signal",
      "ai_signals": [],
      "ai_noise": [],
      "title_original": "思林杰：股东拟合计减持不超6%股份",
      "title_en": null,
      "title_zh": "思林杰：股东拟合计减持不超6%股份",
      "title_bilingual": "思林杰：股东拟合计减持不超6%股份"
    },
    {
      "id": "91dd522f9a478bfacde69f1628aeba2d38767080",
      "site_id": "opmlrss",
      "site_name": "OPML RSS",
      "source": "36氪 - AI",
      "title": "艾德生物：筹划控制权变更事项，股票停牌",
      "url": "https://36kr.com/newsflashes/3832893336888968?f=rss",
      "published_at": "2026-05-31T09:33:36Z",
      "first_seen_at": "2026-05-31T11:41:54.440430Z",
      "last_seen_at": "2026-05-31T13:49:50.572130Z",
      "ai_is_related": true,
      "ai_score": 0.67,
      "ai_label": "ai_general",
      "ai_relevance_reason": "matched_ai_signal",
      "ai_signals": [],
      "ai_noise": [],
      "title_original": "艾德生物：筹划控制权变更事项，股票停牌",
      "title_en": null,
      "title_zh": "艾德生物：筹划控制权变更事项，股票停牌",
      "title_bilingual": "艾德生物：筹划控制权变更事项，股票停牌"
    },
    {
      "id": "3ccb5fa0c314e9ceda21a64e3adba4c9622e5c7c",
      "site_id": "opmlrss",
      "site_name": "OPML RSS",
      "source": "36氪 - AI",
      "title": "风华高科：不涉及英伟达认证及暂停接单传闻不实",
      "url": "https://36kr.com/newsflashes/3832892582553221?f=rss",
      "published_at": "2026-05-31T09:01:50Z",
      "first_seen_at": "2026-05-31T09:32:51.087280Z",
      "last_seen_at": "2026-05-31T13:49:50.572130Z",
      "ai_is_related": true,
      "ai_score": 0.67,
      "ai_label": "ai_general",
      "ai_relevance_reason": "matched_ai_signal",
      "ai_signals": [],
      "ai_noise": [],
      "title_original": "风华高科：不涉及英伟达认证及暂停接单传闻不实",
      "title_en": null,
      "title_zh": "风华高科：不涉及英伟达认证及暂停接单传闻不实",
      "title_bilingual": "风华高科：不涉及英伟达认证及暂停接单传闻不实"
    },
    {
      "id": "bce37ce492ee91dadf8c26351a4394662b1bcbdc",
      "site_id": "opmlrss",
      "site_name": "OPML RSS",
      "source": "36氪 - AI",
      "title": "华金证券：6月A股继续震荡偏强，科技主线不变",
      "url": "https://36kr.com/newsflashes/3832869930952327?f=rss",
      "published_at": "2026-05-31T08:53:45Z",
      "first_seen_at": "2026-05-31T09:32:51.087280Z",
      "last_seen_at": "2026-05-31T13:49:50.572130Z",
      "ai_is_related": true,
      "ai_score": 0.67,
      "ai_label": "ai_general",
      "ai_relevance_reason": "matched_ai_signal",
      "ai_signals": [],
      "ai_noise": [],
      "title_original": "华金证券：6月A股继续震荡偏强，科技主线不变",
      "title_en": null,
      "title_zh": "华金证券：6月A股继续震荡偏强，科技主线不变",
      "title_bilingual": "华金证券：6月A股继续震荡偏强，科技主线不变"
    },
    {
      "id": "82876441d60aceff49d2284bc58b2bf45d66d8e5",
      "site_id": "opmlrss",
      "site_name": "OPML RSS",
      "source": "36氪 - AI",
      "title": "浙大网新：ZH12数据中心第3个模块签署服务合同，预计总收入4.48亿元",
      "url": "https://36kr.com/newsflashes/3832894774011777?f=rss",
      "published_at": "2026-05-31T08:47:05Z",
      "first_seen_at": "2026-05-31T09:32:51.087280Z",
      "last_seen_at": "2026-05-31T13:49:50.572130Z",
      "ai_is_related": true,
      "ai_score": 0.67,
      "ai_label": "ai_general",
      "ai_relevance_reason": "matched_ai_signal",
      "ai_signals": [],
      "ai_noise": [],
      "title_original": "浙大网新：ZH12数据中心第3个模块签署服务合同，预计总收入4.48亿元",
      "title_en": null,
      "title_zh": "浙大网新：ZH12数据中心第3个模块签署服务合同，预计总收入4.48亿元",
      "title_bilingual": "浙大网新：ZH12数据中心第3个模块签署服务合同，预计总收入4.48亿元"
    },
    {
      "id": "e5297f0af10e966953404392d86a443c89860ce5",
      "site_id": "opmlrss",
      "site_name": "OPML RSS",
      "source": "36氪 - AI",
      "title": "印度储备银行4月美元净空头头寸降至953亿美元",
      "url": "https://36kr.com/newsflashes/3832868888962947?f=rss",
      "published_at": "2026-05-31T08:16:43Z",
      "first_seen_at": "2026-05-31T09:32:51.087280Z",
      "last_seen_at": "2026-05-31T13:49:50.572130Z",
      "ai_is_related": true,
      "ai_score": 0.67,
      "ai_label": "ai_general",
      "ai_relevance_reason": "matched_ai_signal",
      "ai_signals": [],
      "ai_noise": [],
      "title_original": "印度储备银行4月美元净空头头寸降至953亿美元",
      "title_en": null,
      "title_zh": "印度储备银行4月美元净空头头寸降至953亿美元",
      "title_bilingual": "印度储备银行4月美元净空头头寸降至953亿美元"
    },
    {
      "id": "a448abf2cb5bcf574b148797ee8c4e43c33241f8",
      "site_id": "opmlrss",
      "site_name": "OPML RSS",
      "source": "36氪 - AI",
      "title": "3C认证实施规则迎来新调整，移动电源新增多项安全测试",
      "url": "https://36kr.com/newsflashes/3832863626192768?f=rss",
      "published_at": "2026-05-31T07:59:16Z",
      "first_seen_at": "2026-05-31T09:32:51.087280Z",
      "last_seen_at": "2026-05-31T13:49:50.572130Z",
      "ai_is_related": true,
      "ai_score": 0.67,
      "ai_label": "ai_general",
      "ai_relevance_reason": "matched_ai_signal",
      "ai_signals": [],
      "ai_noise": [],
      "title_original": "3C认证实施规则迎来新调整，移动电源新增多项安全测试",
      "title_en": null,
      "title_zh": "3C认证实施规则迎来新调整，移动电源新增多项安全测试",
      "title_bilingual": "3C认证实施规则迎来新调整，移动电源新增多项安全测试"
    },
    {
      "id": "380c44ab2be6968b1b136e14032fe327e6e00c5e",
      "site_id": "opmlrss",
      "site_name": "OPML RSS",
      "source": "36氪 - AI",
      "title": "嘉美包装：要约收购期限届满，股票自6月1日起停牌",
      "url": "https://36kr.com/newsflashes/3832894300153472?f=rss",
      "published_at": "2026-05-31T07:54:36Z",
      "first_seen_at": "2026-05-31T09:32:51.087280Z",
      "last_seen_at": "2026-05-31T13:49:50.572130Z",
      "ai_is_related": true,
      "ai_score": 0.67,
      "ai_label": "industry_business",
      "ai_relevance_reason": "matched_ai_signal",
      "ai_signals": [],
      "ai_noise": [],
      "title_original": "嘉美包装：要约收购期限届满，股票自6月1日起停牌",
      "title_en": null,
      "title_zh": "嘉美包装：要约收购期限届满，股票自6月1日起停牌",
      "title_bilingual": "嘉美包装：要约收购期限届满，股票自6月1日起停牌"
    },
    {
      "id": "6716779819fb153c19ee641a706bf00d7db76478",
      "site_id": "opmlrss",
      "site_name": "OPML RSS",
      "source": "36氪 - AI",
      "title": "宝鼎科技：公司未与英伟达有过接触或业务合作，目前未有高速覆铜板M7和M9产品销售",
      "url": "https://36kr.com/newsflashes/3832893774391173?f=rss",
      "published_at": "2026-05-31T07:41:10Z",
      "first_seen_at": "2026-05-31T09:32:51.087280Z",
      "last_seen_at": "2026-05-31T13:49:50.572130Z",
      "ai_is_related": true,
      "ai_score": 0.67,
      "ai_label": "industry_business",
      "ai_relevance_reason": "matched_ai_signal",
      "ai_signals": [],
      "ai_noise": [],
      "title_original": "宝鼎科技：公司未与英伟达有过接触或业务合作，目前未有高速覆铜板M7和M9产品销售",
      "title_en": null,
      "title_zh": "宝鼎科技：公司未与英伟达有过接触或业务合作，目前未有高速覆铜板M7和M9产品销售",
      "title_bilingual": "宝鼎科技：公司未与英伟达有过接触或业务合作，目前未有高速覆铜板M7和M9产品销售"
    },
    {
      "id": "5a12c1cd5ec98ecb60994447f47e9d66f05383a6",
      "site_id": "opmlrss",
      "site_name": "OPML RSS",
      "source": "36氪 - AI",
      "title": "百诚医药：终止筹划控制权变更事项，股票复牌",
      "url": "https://36kr.com/newsflashes/3832891865180035?f=rss",
      "published_at": "2026-05-31T07:39:13Z",
      "first_seen_at": "2026-05-31T09:32:51.087280Z",
      "last_seen_at": "2026-05-31T13:49:50.572130Z",
      "ai_is_related": true,
      "ai_score": 0.67,
      "ai_label": "ai_general",
      "ai_relevance_reason": "matched_ai_signal",
      "ai_signals": [],
      "ai_noise": [],
      "title_original": "百诚医药：终止筹划控制权变更事项，股票复牌",
      "title_en": null,
      "title_zh": "百诚医药：终止筹划控制权变更事项，股票复牌",
      "title_bilingual": "百诚医药：终止筹划控制权变更事项，股票复牌"
    },
    {
      "id": "47570de53b948b1353168fe041e753317444a383",
      "site_id": "opmlrss",
      "site_name": "OPML RSS",
      "source": "36氪 - AI",
      "title": "申万宏源：短期结构分化走向极致，市场再突破仍需蓄力",
      "url": "https://36kr.com/newsflashes/3832743456695943?f=rss",
      "published_at": "2026-05-31T07:28:09Z",
      "first_seen_at": "2026-05-31T09:32:51.087280Z",
      "last_seen_at": "2026-05-31T13:49:50.572130Z",
      "ai_is_related": true,
      "ai_score": 0.67,
      "ai_label": "ai_general",
      "ai_relevance_reason": "matched_ai_signal",
      "ai_signals": [],
      "ai_noise": [],
      "title_original": "申万宏源：短期结构分化走向极致，市场再突破仍需蓄力",
      "title_en": null,
      "title_zh": "申万宏源：短期结构分化走向极致，市场再突破仍需蓄力",
      "title_bilingual": "申万宏源：短期结构分化走向极致，市场再突破仍需蓄力"
    },
    {
      "id": "b1996f0df111a625e73b544af5bebf5744b3642f",
      "site_id": "opmlrss",
      "site_name": "OPML RSS",
      "source": "36氪 - AI",
      "title": "韩国外汇委员会：韩国将于7月6日启动韩元全天候外汇交易",
      "url": "https://36kr.com/newsflashes/3832742483568258?f=rss",
      "published_at": "2026-05-31T07:01:08Z",
      "first_seen_at": "2026-05-31T09:32:51.087280Z",
      "last_seen_at": "2026-05-31T13:49:50.572130Z",
      "ai_is_related": true,
      "ai_score": 0.67,
      "ai_label": "ai_general",
      "ai_relevance_reason": "matched_ai_signal",
      "ai_signals": [],
      "ai_noise": [],
      "title_original": "韩国外汇委员会：韩国将于7月6日启动韩元全天候外汇交易",
      "title_en": null,
      "title_zh": "韩国外汇委员会：韩国将于7月6日启动韩元全天候外汇交易",
      "title_bilingual": "韩国外汇委员会：韩国将于7月6日启动韩元全天候外汇交易"
    },
    {
      "id": "f5e15590245c6de7a67691e1600759dd7d006b73",
      "site_id": "opmlrss",
      "site_name": "OPML RSS",
      "source": "36氪 - AI",
      "title": "深圳800元养老消费券来了",
      "url": "https://36kr.com/newsflashes/3832741808645764?f=rss",
      "published_at": "2026-05-31T06:31:28Z",
      "first_seen_at": "2026-05-31T09:32:51.087280Z",
      "last_seen_at": "2026-05-31T13:49:50.572130Z",
      "ai_is_related": true,
      "ai_score": 0.67,
      "ai_label": "ai_general",
      "ai_relevance_reason": "matched_ai_signal",
      "ai_signals": [],
      "ai_noise": [],
      "title_original": "深圳800元养老消费券来了",
      "title_en": null,
      "title_zh": "深圳800元养老消费券来了",
      "title_bilingual": "深圳800元养老消费券来了"
    },
    {
      "id": "76414e35f99054da2a8e5f127df2c4371386c83f",
      "site_id": "opmlrss",
      "site_name": "OPML RSS",
      "source": "36氪 - AI",
      "title": "17股上榜本周南向资金成交活跃股名单",
      "url": "https://36kr.com/newsflashes/3832740552075138?f=rss",
      "published_at": "2026-05-31T06:10:12Z",
      "first_seen_at": "2026-05-31T06:21:59.231013Z",
      "last_seen_at": "2026-05-31T13:49:50.572130Z",
      "ai_is_related": true,
      "ai_score": 0.67,
      "ai_label": "ai_general",
      "ai_relevance_reason": "matched_ai_signal",
      "ai_signals": [],
      "ai_noise": [],
      "title_original": "17股上榜本周南向资金成交活跃股名单",
      "title_en": null,
      "title_zh": "17股上榜本周南向资金成交活跃股名单",
      "title_bilingual": "17股上榜本周南向资金成交活跃股名单"
    },
    {
      "id": "5c4eeb3575a0783c887b45d2a9762259ce78295a",
      "site_id": "opmlrss",
      "site_name": "OPML RSS",
      "source": "36氪 - AI",
      "title": "美团披露公益数据：6.2亿用户助力建成超5000座乡村儿童操场",
      "url": "https://36kr.com/newsflashes/3832739990972038?f=rss",
      "published_at": "2026-05-31T05:44:35Z",
      "first_seen_at": "2026-05-31T06:21:59.231013Z",
      "last_seen_at": "2026-05-31T13:49:50.572130Z",
      "ai_is_related": true,
      "ai_score": 0.67,
      "ai_label": "ai_general",
      "ai_relevance_reason": "matched_ai_signal",
      "ai_signals": [],
      "ai_noise": [],
      "title_original": "美团披露公益数据：6.2亿用户助力建成超5000座乡村儿童操场",
      "title_en": null,
      "title_zh": "美团披露公益数据：6.2亿用户助力建成超5000座乡村儿童操场",
      "title_bilingual": "美团披露公益数据：6.2亿用户助力建成超5000座乡村儿童操场"
    },
    {
      "id": "761fcaacb9fecf55950b0b99796a975f9ad38e37",
      "site_id": "opmlrss",
      "site_name": "OPML RSS",
      "source": "36氪 - AI",
      "title": "我国儿童新药连续五年增长，2025年批准138个",
      "url": "https://36kr.com/newsflashes/3832730058565512?f=rss",
      "published_at": "2026-05-31T05:21:30Z",
      "first_seen_at": "2026-05-31T06:21:59.231013Z",
      "last_seen_at": "2026-05-31T13:49:50.572130Z",
      "ai_is_related": true,
      "ai_score": 0.67,
      "ai_label": "ai_general",
      "ai_relevance_reason": "matched_ai_signal",
      "ai_signals": [],
      "ai_noise": [],
      "title_original": "我国儿童新药连续五年增长，2025年批准138个",
      "title_en": null,
      "title_zh": "我国儿童新药连续五年增长，2025年批准138个",
      "title_bilingual": "我国儿童新药连续五年增长，2025年批准138个"
    },
    {
      "id": "d56363a9ef683b452d63f5a1ab4c6e9ee34cc654",
      "site_id": "opmlrss",
      "site_name": "OPML RSS",
      "source": "36氪 - AI",
      "title": "银轮股份：为数据中心用大马力发电机组配套大型冷却模块已量产",
      "url": "https://36kr.com/newsflashes/3832661750572930?f=rss",
      "published_at": "2026-05-31T04:50:03Z",
      "first_seen_at": "2026-05-31T06:21:59.231013Z",
      "last_seen_at": "2026-05-31T13:49:50.572130Z",
      "ai_is_related": true,
      "ai_score": 0.67,
      "ai_label": "ai_general",
      "ai_relevance_reason": "matched_ai_signal",
      "ai_signals": [],
      "ai_noise": [],
      "title_original": "银轮股份：为数据中心用大马力发电机组配套大型冷却模块已量产",
      "title_en": null,
      "title_zh": "银轮股份：为数据中心用大马力发电机组配套大型冷却模块已量产",
      "title_bilingual": "银轮股份：为数据中心用大马力发电机组配套大型冷却模块已量产"
    },
    {
      "id": "814a5448b18553864a30abdad9f6807da195f773",
      "site_id": "opmlrss",
      "site_name": "OPML RSS",
      "source": "36氪 - AI",
      "title": "软银承诺斥资750亿欧元在法国建设人工智能设施",
      "url": "https://36kr.com/newsflashes/3832585694193541?f=rss",
      "published_at": "2026-05-31T04:32:41Z",
      "first_seen_at": "2026-05-31T06:21:59.231013Z",
      "last_seen_at": "2026-05-31T13:49:50.572130Z",
      "ai_is_related": true,
      "ai_score": 0.71,
      "ai_label": "ai_general",
      "ai_relevance_reason": "matched_ai_signal",
      "ai_signals": [
        "人工智能"
      ],
      "ai_noise": [],
      "title_original": "软银承诺斥资750亿欧元在法国建设人工智能设施",
      "title_en": null,
      "title_zh": "软银承诺斥资750亿欧元在法国建设人工智能设施",
      "title_bilingual": "软银承诺斥资750亿欧元在法国建设人工智能设施"
    },
    {
      "id": "0d7f41427091db3edd3ebbf1fcc34a8002cf0f83",
      "site_id": "opmlrss",
      "site_name": "OPML RSS",
      "source": "36氪 - AI",
      "title": "收获进度18.18%，全国冬小麦机收进度逐步加快",
      "url": "https://36kr.com/newsflashes/3832526695851908?f=rss",
      "published_at": "2026-05-31T03:57:39Z",
      "first_seen_at": "2026-05-31T06:21:59.231013Z",
      "last_seen_at": "2026-05-31T13:49:50.572130Z",
      "ai_is_related": true,
      "ai_score": 0.67,
      "ai_label": "ai_general",
      "ai_relevance_reason": "matched_ai_signal",
      "ai_signals": [],
      "ai_noise": [],
      "title_original": "收获进度18.18%，全国冬小麦机收进度逐步加快",
      "title_en": null,
      "title_zh": "收获进度18.18%，全国冬小麦机收进度逐步加快",
      "title_bilingual": "收获进度18.18%，全国冬小麦机收进度逐步加快"
    },
    {
      "id": "96859506153b0c67c94c8c3db4243456b5e640e9",
      "site_id": "opmlrss",
      "site_name": "OPML RSS",
      "source": "36氪 - AI",
      "title": "前4个月我国软件业务收入46686亿元，同比增长10.9%",
      "url": "https://36kr.com/newsflashes/3832525421635200?f=rss",
      "published_at": "2026-05-31T03:31:23Z",
      "first_seen_at": "2026-05-31T06:21:59.231013Z",
      "last_seen_at": "2026-05-31T13:49:50.572130Z",
      "ai_is_related": true,
      "ai_score": 0.7,
      "ai_label": "ai_tech",
      "ai_relevance_reason": "matched_ai_signal",
      "ai_signals": [
        "软件"
      ],
      "ai_noise": [],
      "title_original": "前4个月我国软件业务收入46686亿元，同比增长10.9%",
      "title_en": null,
      "title_zh": "前4个月我国软件业务收入46686亿元，同比增长10.9%",
      "title_bilingual": "前4个月我国软件业务收入46686亿元，同比增长10.9%"
    },
    {
      "id": "4dbfedb7e1d942b4d7091f8a9e1c06e92fc95aaf",
      "site_id": "opmlrss",
      "site_name": "OPML RSS",
      "source": "36氪 - AI",
      "title": "国家医保局发布2026年国家医保目录调整工作方案",
      "url": "https://36kr.com/newsflashes/3832518583428736?f=rss",
      "published_at": "2026-05-31T02:59:23Z",
      "first_seen_at": "2026-05-31T06:21:59.231013Z",
      "last_seen_at": "2026-05-31T09:32:51.087280Z",
      "ai_is_related": true,
      "ai_score": 0.67,
      "ai_label": "model_release",
      "ai_relevance_reason": "matched_ai_signal",
      "ai_signals": [],
      "ai_noise": [],
      "title_original": "国家医保局发布2026年国家医保目录调整工作方案",
      "title_en": null,
      "title_zh": "国家医保局发布2026年国家医保目录调整工作方案",
      "title_bilingual": "国家医保局发布2026年国家医保目录调整工作方案"
    },
    {
      "id": "17a8363db8574ac8f71ed6efe19ba0e5e47c6c59",
      "site_id": "opmlrss",
      "site_name": "OPML RSS",
      "source": "36氪 - AI",
      "title": "中国汽车流通协会：5月中国汽车经销商库存预警指数为57.9%",
      "url": "https://36kr.com/newsflashes/3832514855839617?f=rss",
      "published_at": "2026-05-31T02:37:32Z",
      "first_seen_at": "2026-05-31T06:21:59.231013Z",
      "last_seen_at": "2026-05-31T09:32:51.087280Z",
      "ai_is_related": true,
      "ai_score": 0.67,
      "ai_label": "ai_general",
      "ai_relevance_reason": "matched_ai_signal",
      "ai_signals": [],
      "ai_noise": [],
      "title_original": "中国汽车流通协会：5月中国汽车经销商库存预警指数为57.9%",
      "title_en": null,
      "title_zh": "中国汽车流通协会：5月中国汽车经销商库存预警指数为57.9%",
      "title_bilingual": "中国汽车流通协会：5月中国汽车经销商库存预警指数为57.9%"
    },
    {
      "id": "6649d6f533a1e60cd7b9e5e7a82605a1f895bc6f",
      "site_id": "opmlrss",
      "site_name": "OPML RSS",
      "source": "36氪 - AI",
      "title": "国家统计局：5月份，制造业采购经理指数（PMI）为50.0%",
      "url": "https://36kr.com/newsflashes/3832582533326471?f=rss",
      "published_at": "2026-05-31T02:24:33Z",
      "first_seen_at": "2026-05-31T06:21:59.231013Z",
      "last_seen_at": "2026-05-31T06:21:59.231013Z",
      "ai_is_related": true,
      "ai_score": 0.67,
      "ai_label": "ai_general",
      "ai_relevance_reason": "matched_ai_signal",
      "ai_signals": [],
      "ai_noise": [],
      "title_original": "国家统计局：5月份，制造业采购经理指数（PMI）为50.0%",
      "title_en": null,
      "title_zh": "国家统计局：5月份，制造业采购经理指数（PMI）为50.0%",
      "title_bilingual": "国家统计局：5月份，制造业采购经理指数（PMI）为50.0%"
    },
    {
      "id": "1fcb90f7cb992f02eafdd141dde0b230d8432d13",
      "site_id": "opmlrss",
      "site_name": "OPML RSS",
      "source": "36氪 - AI",
      "title": "天猫618：多品牌手机集体降价，iPhone降2500元，华为降3500元",
      "url": "https://36kr.com/newsflashes/3832582092252808?f=rss",
      "published_at": "2026-05-31T02:24:06Z",
      "first_seen_at": "2026-05-31T06:21:59.231013Z",
      "last_seen_at": "2026-05-31T06:21:59.231013Z",
      "ai_is_related": true,
      "ai_score": 0.65,
      "ai_label": "ai_general",
      "ai_relevance_reason": "matched_ai_signal",
      "ai_signals": [],
      "ai_noise": [
        "天猫"
      ],
      "title_original": "天猫618：多品牌手机集体降价，iPhone降2500元，华为降3500元",
      "title_en": null,
      "title_zh": "天猫618：多品牌手机集体降价，iPhone降2500元，华为降3500元",
      "title_bilingual": "天猫618：多品牌手机集体降价，iPhone降2500元，华为降3500元"
    },
    {
      "id": "92897588e6d0f0495e59b562470a3cee23decfbd",
      "site_id": "opmlrss",
      "site_name": "OPML RSS",
      "source": "36氪 - AI",
      "title": "预计减免关税近600万元，封关后首架“零关税”客机通关",
      "url": "https://36kr.com/newsflashes/3832506934388354?f=rss",
      "published_at": "2026-05-31T02:12:33Z",
      "first_seen_at": "2026-05-31T06:21:59.231013Z",
      "last_seen_at": "2026-05-31T06:21:59.231013Z",
      "ai_is_related": true,
      "ai_score": 0.67,
      "ai_label": "ai_general",
      "ai_relevance_reason": "matched_ai_signal",
      "ai_signals": [],
      "ai_noise": [],
      "title_original": "预计减免关税近600万元，封关后首架“零关税”客机通关",
      "title_en": null,
      "title_zh": "预计减免关税近600万元，封关后首架“零关税”客机通关",
      "title_bilingual": "预计减免关税近600万元，封关后首架“零关税”客机通关"
    },
    {
      "id": "f93e876de4705db3183aaa3d43f87f80209e8886",
      "site_id": "opmlrss",
      "site_name": "OPML RSS",
      "source": "36氪 - AI",
      "title": "智元机器人合伙人姚卯青：今年上半年智元海外收入占比已近20%",
      "url": "https://36kr.com/newsflashes/3832506045818500?f=rss",
      "published_at": "2026-05-31T01:58:39Z",
      "first_seen_at": "2026-05-31T06:21:59.231013Z",
      "last_seen_at": "2026-05-31T06:21:59.231013Z",
      "ai_is_related": true,
      "ai_score": 0.7,
      "ai_label": "robotics",
      "ai_relevance_reason": "matched_ai_signal",
      "ai_signals": [
        "机器人"
      ],
      "ai_noise": [],
      "title_original": "智元机器人合伙人姚卯青：今年上半年智元海外收入占比已近20%",
      "title_en": null,
      "title_zh": "智元机器人合伙人姚卯青：今年上半年智元海外收入占比已近20%",
      "title_bilingual": "智元机器人合伙人姚卯青：今年上半年智元海外收入占比已近20%"
    },
    {
      "id": "24f82e4d86f2d40930096ab96ee89257cf49f2a1",
      "site_id": "opmlrss",
      "site_name": "OPML RSS",
      "source": "36氪 - AI",
      "title": "欧洲央行管委佩雷拉：必须尽早应对通胀",
      "url": "https://36kr.com/newsflashes/3832504586577798?f=rss",
      "published_at": "2026-05-31T01:28:09Z",
      "first_seen_at": "2026-05-31T01:34:42.347252Z",
      "last_seen_at": "2026-05-31T06:21:59.231013Z",
      "ai_is_related": true,
      "ai_score": 0.67,
      "ai_label": "ai_general",
      "ai_relevance_reason": "matched_ai_signal",
      "ai_signals": [],
      "ai_noise": [],
      "title_original": "欧洲央行管委佩雷拉：必须尽早应对通胀",
      "title_en": null,
      "title_zh": "欧洲央行管委佩雷拉：必须尽早应对通胀",
      "title_bilingual": "欧洲央行管委佩雷拉：必须尽早应对通胀"
    },
    {
      "id": "c28bec3db1d49b936f08a671169fe0079b3f604e",
      "site_id": "opmlrss",
      "site_name": "OPML RSS",
      "source": "36氪 - AI",
      "title": "小米技术：MiMo-V2.5实现五大核心突破，降价后仍能实现收支平衡",
      "url": "https://36kr.com/newsflashes/3832525007284097?f=rss",
      "published_at": "2026-05-31T01:26:02Z",
      "first_seen_at": "2026-05-31T01:34:42.347252Z",
      "last_seen_at": "2026-05-31T06:21:59.231013Z",
      "ai_is_related": true,
      "ai_score": 0.7,
      "ai_label": "ai_tech",
      "ai_relevance_reason": "matched_ai_signal",
      "ai_signals": [
        "技术"
      ],
      "ai_noise": [],
      "title_original": "小米技术：MiMo-V2.5实现五大核心突破，降价后仍能实现收支平衡",
      "title_en": null,
      "title_zh": "小米技术：MiMo-V2.5实现五大核心突破，降价后仍能实现收支平衡",
      "title_bilingual": "小米技术：MiMo-V2.5实现五大核心突破，降价后仍能实现收支平衡"
    },
    {
      "id": "203fd3e3f8b8609df49cc1e8f59c91de57c6a7de",
      "site_id": "opmlrss",
      "site_name": "OPML RSS",
      "source": "36氪 - AI",
      "title": "丰田回应将中止雷克萨斯下一代纯电轿车开发",
      "url": "https://36kr.com/newsflashes/3832495904171908?f=rss",
      "published_at": "2026-05-31T01:15:06Z",
      "first_seen_at": "2026-05-31T01:34:42.347252Z",
      "last_seen_at": "2026-05-31T06:21:59.231013Z",
      "ai_is_related": true,
      "ai_score": 0.67,
      "ai_label": "ai_general",
      "ai_relevance_reason": "matched_ai_signal",
      "ai_signals": [],
      "ai_noise": [],
      "title_original": "丰田回应将中止雷克萨斯下一代纯电轿车开发",
      "title_en": null,
      "title_zh": "丰田回应将中止雷克萨斯下一代纯电轿车开发",
      "title_bilingual": "丰田回应将中止雷克萨斯下一代纯电轿车开发"
    },
    {
      "id": "f57fc5a0700296e99a45a4386670deeec4bd8f0f",
      "site_id": "opmlrss",
      "site_name": "OPML RSS",
      "source": "36氪 - AI",
      "title": "我国成功发射卫星互联网技术试验卫星",
      "url": "https://36kr.com/newsflashes/3832495203657606?f=rss",
      "published_at": "2026-05-31T00:55:43Z",
      "first_seen_at": "2026-05-31T01:34:42.347252Z",
      "last_seen_at": "2026-05-31T06:21:59.231013Z",
      "ai_is_related": true,
      "ai_score": 0.7,
      "ai_label": "ai_tech",
      "ai_relevance_reason": "matched_ai_signal",
      "ai_signals": [
        "技术"
      ],
      "ai_noise": [],
      "title_original": "我国成功发射卫星互联网技术试验卫星",
      "title_en": null,
      "title_zh": "我国成功发射卫星互联网技术试验卫星",
      "title_bilingual": "我国成功发射卫星互联网技术试验卫星"
    },
    {
      "id": "58df2b85c3dbbcf5621be08d742aa4ee12061e8e",
      "site_id": "opmlrss",
      "site_name": "OPML RSS",
      "source": "ReadHub",
      "title": "软银承诺斥资 750 亿欧元在法国建设人工智能设施",
      "url": "https://readhub.cn/topic/8tYwZwF7BvS",
      "published_at": "2026-05-30T20:54:56Z",
      "first_seen_at": "2026-05-30T21:34:07.181560Z",
      "last_seen_at": "2026-05-31T13:49:50.572130Z",
      "ai_is_related": true,
      "ai_score": 0.71,
      "ai_label": "ai_general",
      "ai_relevance_reason": "matched_ai_signal",
      "ai_signals": [
        "人工智能"
      ],
      "ai_noise": [],
      "title_original": "软银承诺斥资 750 亿欧元在法国建设人工智能设施",
      "title_en": null,
      "title_zh": "软银承诺斥资 750 亿欧元在法国建设人工智能设施",
      "title_bilingual": "软银承诺斥资 750 亿欧元在法国建设人工智能设施"
    }
  ],
  "items_ai": [
    {
      "id": "d00109d4c89faa4b99109ecfcf1739cb8fbdc65c",
      "site_id": "opmlrss",
      "site_name": "OPML RSS",
      "source": "36氪 - AI",
      "title": "思林杰：股东拟合计减持不超6%股份",
      "url": "https://36kr.com/newsflashes/3832895152187009?f=rss",
      "published_at": "2026-05-31T09:47:29Z",
      "first_seen_at": "2026-05-31T11:41:54.440430Z",
      "last_seen_at": "2026-05-31T13:49:50.572130Z",
      "ai_is_related": true,
      "ai_score": 0.67,
      "ai_label": "ai_general",
      "ai_relevance_reason": "matched_ai_signal",
      "ai_signals": [],
      "ai_noise": [],
      "title_original": "思林杰：股东拟合计减持不超6%股份",
      "title_en": null,
      "title_zh": "思林杰：股东拟合计减持不超6%股份",
      "title_bilingual": "思林杰：股东拟合计减持不超6%股份"
    },
    {
      "id": "91dd522f9a478bfacde69f1628aeba2d38767080",
      "site_id": "opmlrss",
      "site_name": "OPML RSS",
      "source": "36氪 - AI",
      "title": "艾德生物：筹划控制权变更事项，股票停牌",
      "url": "https://36kr.com/newsflashes/3832893336888968?f=rss",
      "published_at": "2026-05-31T09:33:36Z",
      "first_seen_at": "2026-05-31T11:41:54.440430Z",
      "last_seen_at": "2026-05-31T13:49:50.572130Z",
      "ai_is_related": true,
      "ai_score": 0.67,
      "ai_label": "ai_general",
      "ai_relevance_reason": "matched_ai_signal",
      "ai_signals": [],
      "ai_noise": [],
      "title_original": "艾德生物：筹划控制权变更事项，股票停牌",
      "title_en": null,
      "title_zh": "艾德生物：筹划控制权变更事项，股票停牌",
      "title_bilingual": "艾德生物：筹划控制权变更事项，股票停牌"
    },
    {
      "id": "3ccb5fa0c314e9ceda21a64e3adba4c9622e5c7c",
      "site_id": "opmlrss",
      "site_name": "OPML RSS",
      "source": "36氪 - AI",
      "title": "风华高科：不涉及英伟达认证及暂停接单传闻不实",
      "url": "https://36kr.com/newsflashes/3832892582553221?f=rss",
      "published_at": "2026-05-31T09:01:50Z",
      "first_seen_at": "2026-05-31T09:32:51.087280Z",
      "last_seen_at": "2026-05-31T13:49:50.572130Z",
      "ai_is_related": true,
      "ai_score": 0.67,
      "ai_label": "ai_general",
      "ai_relevance_reason": "matched_ai_signal",
      "ai_signals": [],
      "ai_noise": [],
      "title_original": "风华高科：不涉及英伟达认证及暂停接单传闻不实",
      "title_en": null,
      "title_zh": "风华高科：不涉及英伟达认证及暂停接单传闻不实",
      "title_bilingual": "风华高科：不涉及英伟达认证及暂停接单传闻不实"
    },
    {
      "id": "bce37ce492ee91dadf8c26351a4394662b1bcbdc",
      "site_id": "opmlrss",
      "site_name": "OPML RSS",
      "source": "36氪 - AI",
      "title": "华金证券：6月A股继续震荡偏强，科技主线不变",
      "url": "https://36kr.com/newsflashes/3832869930952327?f=rss",
      "published_at": "2026-05-31T08:53:45Z",
      "first_seen_at": "2026-05-31T09:32:51.087280Z",
      "last_seen_at": "2026-05-31T13:49:50.572130Z",
      "ai_is_related": true,
      "ai_score": 0.67,
      "ai_label": "ai_general",
      "ai_relevance_reason": "matched_ai_signal",
      "ai_signals": [],
      "ai_noise": [],
      "title_original": "华金证券：6月A股继续震荡偏强，科技主线不变",
      "title_en": null,
      "title_zh": "华金证券：6月A股继续震荡偏强，科技主线不变",
      "title_bilingual": "华金证券：6月A股继续震荡偏强，科技主线不变"
    },
    {
      "id": "82876441d60aceff49d2284bc58b2bf45d66d8e5",
      "site_id": "opmlrss",
      "site_name": "OPML RSS",
      "source": "36氪 - AI",
      "title": "浙大网新：ZH12数据中心第3个模块签署服务合同，预计总收入4.48亿元",
      "url": "https://36kr.com/newsflashes/3832894774011777?f=rss",
      "published_at": "2026-05-31T08:47:05Z",
      "first_seen_at": "2026-05-31T09:32:51.087280Z",
      "last_seen_at": "2026-05-31T13:49:50.572130Z",
      "ai_is_related": true,
      "ai_score": 0.67,
      "ai_label": "ai_general",
      "ai_relevance_reason": "matched_ai_signal",
      "ai_signals": [],
      "ai_noise": [],
      "title_original": "浙大网新：ZH12数据中心第3个模块签署服务合同，预计总收入4.48亿元",
      "title_en": null,
      "title_zh": "浙大网新：ZH12数据中心第3个模块签署服务合同，预计总收入4.48亿元",
      "title_bilingual": "浙大网新：ZH12数据中心第3个模块签署服务合同，预计总收入4.48亿元"
    },
    {
      "id": "e5297f0af10e966953404392d86a443c89860ce5",
      "site_id": "opmlrss",
      "site_name": "OPML RSS",
      "source": "36氪 - AI",
      "title": "印度储备银行4月美元净空头头寸降至953亿美元",
      "url": "https://36kr.com/newsflashes/3832868888962947?f=rss",
      "published_at": "2026-05-31T08:16:43Z",
      "first_seen_at": "2026-05-31T09:32:51.087280Z",
      "last_seen_at": "2026-05-31T13:49:50.572130Z",
      "ai_is_related": true,
      "ai_score": 0.67,
      "ai_label": "ai_general",
      "ai_relevance_reason": "matched_ai_signal",
      "ai_signals": [],
      "ai_noise": [],
      "title_original": "印度储备银行4月美元净空头头寸降至953亿美元",
      "title_en": null,
      "title_zh": "印度储备银行4月美元净空头头寸降至953亿美元",
      "title_bilingual": "印度储备银行4月美元净空头头寸降至953亿美元"
    },
    {
      "id": "a448abf2cb5bcf574b148797ee8c4e43c33241f8",
      "site_id": "opmlrss",
      "site_name": "OPML RSS",
      "source": "36氪 - AI",
      "title": "3C认证实施规则迎来新调整，移动电源新增多项安全测试",
      "url": "https://36kr.com/newsflashes/3832863626192768?f=rss",
      "published_at": "2026-05-31T07:59:16Z",
      "first_seen_at": "2026-05-31T09:32:51.087280Z",
      "last_seen_at": "2026-05-31T13:49:50.572130Z",
      "ai_is_related": true,
      "ai_score": 0.67,
      "ai_label": "ai_general",
      "ai_relevance_reason": "matched_ai_signal",
      "ai_signals": [],
      "ai_noise": [],
      "title_original": "3C认证实施规则迎来新调整，移动电源新增多项安全测试",
      "title_en": null,
      "title_zh": "3C认证实施规则迎来新调整，移动电源新增多项安全测试",
      "title_bilingual": "3C认证实施规则迎来新调整，移动电源新增多项安全测试"
    },
    {
      "id": "380c44ab2be6968b1b136e14032fe327e6e00c5e",
      "site_id": "opmlrss",
      "site_name": "OPML RSS",
      "source": "36氪 - AI",
      "title": "嘉美包装：要约收购期限届满，股票自6月1日起停牌",
      "url": "https://36kr.com/newsflashes/3832894300153472?f=rss",
      "published_at": "2026-05-31T07:54:36Z",
      "first_seen_at": "2026-05-31T09:32:51.087280Z",
      "last_seen_at": "2026-05-31T13:49:50.572130Z",
      "ai_is_related": true,
      "ai_score": 0.67,
      "ai_label": "industry_business",
      "ai_relevance_reason": "matched_ai_signal",
      "ai_signals": [],
      "ai_noise": [],
      "title_original": "嘉美包装：要约收购期限届满，股票自6月1日起停牌",
      "title_en": null,
      "title_zh": "嘉美包装：要约收购期限届满，股票自6月1日起停牌",
      "title_bilingual": "嘉美包装：要约收购期限届满，股票自6月1日起停牌"
    },
    {
      "id": "6716779819fb153c19ee641a706bf00d7db76478",
      "site_id": "opmlrss",
      "site_name": "OPML RSS",
      "source": "36氪 - AI",
      "title": "宝鼎科技：公司未与英伟达有过接触或业务合作，目前未有高速覆铜板M7和M9产品销售",
      "url": "https://36kr.com/newsflashes/3832893774391173?f=rss",
      "published_at": "2026-05-31T07:41:10Z",
      "first_seen_at": "2026-05-31T09:32:51.087280Z",
      "last_seen_at": "2026-05-31T13:49:50.572130Z",
      "ai_is_related": true,
      "ai_score": 0.67,
      "ai_label": "industry_business",
      "ai_relevance_reason": "matched_ai_signal",
      "ai_signals": [],
      "ai_noise": [],
      "title_original": "宝鼎科技：公司未与英伟达有过接触或业务合作，目前未有高速覆铜板M7和M9产品销售",
      "title_en": null,
      "title_zh": "宝鼎科技：公司未与英伟达有过接触或业务合作，目前未有高速覆铜板M7和M9产品销售",
      "title_bilingual": "宝鼎科技：公司未与英伟达有过接触或业务合作，目前未有高速覆铜板M7和M9产品销售"
    },
    {
      "id": "5a12c1cd5ec98ecb60994447f47e9d66f05383a6",
      "site_id": "opmlrss",
      "site_name": "OPML RSS",
      "source": "36氪 - AI",
      "title": "百诚医药：终止筹划控制权变更事项，股票复牌",
      "url": "https://36kr.com/newsflashes/3832891865180035?f=rss",
      "published_at": "2026-05-31T07:39:13Z",
      "first_seen_at": "2026-05-31T09:32:51.087280Z",
      "last_seen_at": "2026-05-31T13:49:50.572130Z",
      "ai_is_related": true,
      "ai_score": 0.67,
      "ai_label": "ai_general",
      "ai_relevance_reason": "matched_ai_signal",
      "ai_signals": [],
      "ai_noise": [],
      "title_original": "百诚医药：终止筹划控制权变更事项，股票复牌",
      "title_en": null,
      "title_zh": "百诚医药：终止筹划控制权变更事项，股票复牌",
      "title_bilingual": "百诚医药：终止筹划控制权变更事项，股票复牌"
    },
    {
      "id": "47570de53b948b1353168fe041e753317444a383",
      "site_id": "opmlrss",
      "site_name": "OPML RSS",
      "source": "36氪 - AI",
      "title": "申万宏源：短期结构分化走向极致，市场再突破仍需蓄力",
      "url": "https://36kr.com/newsflashes/3832743456695943?f=rss",
      "published_at": "2026-05-31T07:28:09Z",
      "first_seen_at": "2026-05-31T09:32:51.087280Z",
      "last_seen_at": "2026-05-31T13:49:50.572130Z",
      "ai_is_related": true,
      "ai_score": 0.67,
      "ai_label": "ai_general",
      "ai_relevance_reason": "matched_ai_signal",
      "ai_signals": [],
      "ai_noise": [],
      "title_original": "申万宏源：短期结构分化走向极致，市场再突破仍需蓄力",
      "title_en": null,
      "title_zh": "申万宏源：短期结构分化走向极致，市场再突破仍需蓄力",
      "title_bilingual": "申万宏源：短期结构分化走向极致，市场再突破仍需蓄力"
    },
    {
      "id": "b1996f0df111a625e73b544af5bebf5744b3642f",
      "site_id": "opmlrss",
      "site_name": "OPML RSS",
      "source": "36氪 - AI",
      "title": "韩国外汇委员会：韩国将于7月6日启动韩元全天候外汇交易",
      "url": "https://36kr.com/newsflashes/3832742483568258?f=rss",
      "published_at": "2026-05-31T07:01:08Z",
      "first_seen_at": "2026-05-31T09:32:51.087280Z",
      "last_seen_at": "2026-05-31T13:49:50.572130Z",
      "ai_is_related": true,
      "ai_score": 0.67,
      "ai_label": "ai_general",
      "ai_relevance_reason": "matched_ai_signal",
      "ai_signals": [],
      "ai_noise": [],
      "title_original": "韩国外汇委员会：韩国将于7月6日启动韩元全天候外汇交易",
      "title_en": null,
      "title_zh": "韩国外汇委员会：韩国将于7月6日启动韩元全天候外汇交易",
      "title_bilingual": "韩国外汇委员会：韩国将于7月6日启动韩元全天候外汇交易"
    },
    {
      "id": "f5e15590245c6de7a67691e1600759dd7d006b73",
      "site_id": "opmlrss",
      "site_name": "OPML RSS",
      "source": "36氪 - AI",
      "title": "深圳800元养老消费券来了",
      "url": "https://36kr.com/newsflashes/3832741808645764?f=rss",
      "published_at": "2026-05-31T06:31:28Z",
      "first_seen_at": "2026-05-31T09:32:51.087280Z",
      "last_seen_at": "2026-05-31T13:49:50.572130Z",
      "ai_is_related": true,
      "ai_score": 0.67,
      "ai_label": "ai_general",
      "ai_relevance_reason": "matched_ai_signal",
      "ai_signals": [],
      "ai_noise": [],
      "title_original": "深圳800元养老消费券来了",
      "title_en": null,
      "title_zh": "深圳800元养老消费券来了",
      "title_bilingual": "深圳800元养老消费券来了"
    },
    {
      "id": "76414e35f99054da2a8e5f127df2c4371386c83f",
      "site_id": "opmlrss",
      "site_name": "OPML RSS",
      "source": "36氪 - AI",
      "title": "17股上榜本周南向资金成交活跃股名单",
      "url": "https://36kr.com/newsflashes/3832740552075138?f=rss",
      "published_at": "2026-05-31T06:10:12Z",
      "first_seen_at": "2026-05-31T06:21:59.231013Z",
      "last_seen_at": "2026-05-31T13:49:50.572130Z",
      "ai_is_related": true,
      "ai_score": 0.67,
      "ai_label": "ai_general",
      "ai_relevance_reason": "matched_ai_signal",
      "ai_signals": [],
      "ai_noise": [],
      "title_original": "17股上榜本周南向资金成交活跃股名单",
      "title_en": null,
      "title_zh": "17股上榜本周南向资金成交活跃股名单",
      "title_bilingual": "17股上榜本周南向资金成交活跃股名单"
    },
    {
      "id": "5c4eeb3575a0783c887b45d2a9762259ce78295a",
      "site_id": "opmlrss",
      "site_name": "OPML RSS",
      "source": "36氪 - AI",
      "title": "美团披露公益数据：6.2亿用户助力建成超5000座乡村儿童操场",
      "url": "https://36kr.com/newsflashes/3832739990972038?f=rss",
      "published_at": "2026-05-31T05:44:35Z",
      "first_seen_at": "2026-05-31T06:21:59.231013Z",
      "last_seen_at": "2026-05-31T13:49:50.572130Z",
      "ai_is_related": true,
      "ai_score": 0.67,
      "ai_label": "ai_general",
      "ai_relevance_reason": "matched_ai_signal",
      "ai_signals": [],
      "ai_noise": [],
      "title_original": "美团披露公益数据：6.2亿用户助力建成超5000座乡村儿童操场",
      "title_en": null,
      "title_zh": "美团披露公益数据：6.2亿用户助力建成超5000座乡村儿童操场",
      "title_bilingual": "美团披露公益数据：6.2亿用户助力建成超5000座乡村儿童操场"
    },
    {
      "id": "761fcaacb9fecf55950b0b99796a975f9ad38e37",
      "site_id": "opmlrss",
      "site_name": "OPML RSS",
      "source": "36氪 - AI",
      "title": "我国儿童新药连续五年增长，2025年批准138个",
      "url": "https://36kr.com/newsflashes/3832730058565512?f=rss",
      "published_at": "2026-05-31T05:21:30Z",
      "first_seen_at": "2026-05-31T06:21:59.231013Z",
      "last_seen_at": "2026-05-31T13:49:50.572130Z",
      "ai_is_related": true,
      "ai_score": 0.67,
      "ai_label": "ai_general",
      "ai_relevance_reason": "matched_ai_signal",
      "ai_signals": [],
      "ai_noise": [],
      "title_original": "我国儿童新药连续五年增长，2025年批准138个",
      "title_en": null,
      "title_zh": "我国儿童新药连续五年增长，2025年批准138个",
      "title_bilingual": "我国儿童新药连续五年增长，2025年批准138个"
    },
    {
      "id": "d56363a9ef683b452d63f5a1ab4c6e9ee34cc654",
      "site_id": "opmlrss",
      "site_name": "OPML RSS",
      "source": "36氪 - AI",
      "title": "银轮股份：为数据中心用大马力发电机组配套大型冷却模块已量产",
      "url": "https://36kr.com/newsflashes/3832661750572930?f=rss",
      "published_at": "2026-05-31T04:50:03Z",
      "first_seen_at": "2026-05-31T06:21:59.231013Z",
      "last_seen_at": "2026-05-31T13:49:50.572130Z",
      "ai_is_related": true,
      "ai_score": 0.67,
      "ai_label": "ai_general",
      "ai_relevance_reason": "matched_ai_signal",
      "ai_signals": [],
      "ai_noise": [],
      "title_original": "银轮股份：为数据中心用大马力发电机组配套大型冷却模块已量产",
      "title_en": null,
      "title_zh": "银轮股份：为数据中心用大马力发电机组配套大型冷却模块已量产",
      "title_bilingual": "银轮股份：为数据中心用大马力发电机组配套大型冷却模块已量产"
    },
    {
      "id": "814a5448b18553864a30abdad9f6807da195f773",
      "site_id": "opmlrss",
      "site_name": "OPML RSS",
      "source": "36氪 - AI",
      "title": "软银承诺斥资750亿欧元在法国建设人工智能设施",
      "url": "https://36kr.com/newsflashes/3832585694193541?f=rss",
      "published_at": "2026-05-31T04:32:41Z",
      "first_seen_at": "2026-05-31T06:21:59.231013Z",
      "last_seen_at": "2026-05-31T13:49:50.572130Z",
      "ai_is_related": true,
      "ai_score": 0.71,
      "ai_label": "ai_general",
      "ai_relevance_reason": "matched_ai_signal",
      "ai_signals": [
        "人工智能"
      ],
      "ai_noise": [],
      "title_original": "软银承诺斥资750亿欧元在法国建设人工智能设施",
      "title_en": null,
      "title_zh": "软银承诺斥资750亿欧元在法国建设人工智能设施",
      "title_bilingual": "软银承诺斥资750亿欧元在法国建设人工智能设施"
    },
    {
      "id": "0d7f41427091db3edd3ebbf1fcc34a8002cf0f83",
      "site_id": "opmlrss",
      "site_name": "OPML RSS",
      "source": "36氪 - AI",
      "title": "收获进度18.18%，全国冬小麦机收进度逐步加快",
      "url": "https://36kr.com/newsflashes/3832526695851908?f=rss",
      "published_at": "2026-05-31T03:57:39Z",
      "first_seen_at": "2026-05-31T06:21:59.231013Z",
      "last_seen_at": "2026-05-31T13:49:50.572130Z",
      "ai_is_related": true,
      "ai_score": 0.67,
      "ai_label": "ai_general",
      "ai_relevance_reason": "matched_ai_signal",
      "ai_signals": [],
      "ai_noise": [],
      "title_original": "收获进度18.18%，全国冬小麦机收进度逐步加快",
      "title_en": null,
      "title_zh": "收获进度18.18%，全国冬小麦机收进度逐步加快",
      "title_bilingual": "收获进度18.18%，全国冬小麦机收进度逐步加快"
    },
    {
      "id": "96859506153b0c67c94c8c3db4243456b5e640e9",
      "site_id": "opmlrss",
      "site_name": "OPML RSS",
      "source": "36氪 - AI",
      "title": "前4个月我国软件业务收入46686亿元，同比增长10.9%",
      "url": "https://36kr.com/newsflashes/3832525421635200?f=rss",
      "published_at": "2026-05-31T03:31:23Z",
      "first_seen_at": "2026-05-31T06:21:59.231013Z",
      "last_seen_at": "2026-05-31T13:49:50.572130Z",
      "ai_is_related": true,
      "ai_score": 0.7,
      "ai_label": "ai_tech",
      "ai_relevance_reason": "matched_ai_signal",
      "ai_signals": [
        "软件"
      ],
      "ai_noise": [],
      "title_original": "前4个月我国软件业务收入46686亿元，同比增长10.9%",
      "title_en": null,
      "title_zh": "前4个月我国软件业务收入46686亿元，同比增长10.9%",
      "title_bilingual": "前4个月我国软件业务收入46686亿元，同比增长10.9%"
    },
    {
      "id": "4dbfedb7e1d942b4d7091f8a9e1c06e92fc95aaf",
      "site_id": "opmlrss",
      "site_name": "OPML RSS",
      "source": "36氪 - AI",
      "title": "国家医保局发布2026年国家医保目录调整工作方案",
      "url": "https://36kr.com/newsflashes/3832518583428736?f=rss",
      "published_at": "2026-05-31T02:59:23Z",
      "first_seen_at": "2026-05-31T06:21:59.231013Z",
      "last_seen_at": "2026-05-31T09:32:51.087280Z",
      "ai_is_related": true,
      "ai_score": 0.67,
      "ai_label": "model_release",
      "ai_relevance_reason": "matched_ai_signal",
      "ai_signals": [],
      "ai_noise": [],
      "title_original": "国家医保局发布2026年国家医保目录调整工作方案",
      "title_en": null,
      "title_zh": "国家医保局发布2026年国家医保目录调整工作方案",
      "title_bilingual": "国家医保局发布2026年国家医保目录调整工作方案"
    },
    {
      "id": "17a8363db8574ac8f71ed6efe19ba0e5e47c6c59",
      "site_id": "opmlrss",
      "site_name": "OPML RSS",
      "source": "36氪 - AI",
      "title": "中国汽车流通协会：5月中国汽车经销商库存预警指数为57.9%",
      "url": "https://36kr.com/newsflashes/3832514855839617?f=rss",
      "published_at": "2026-05-31T02:37:32Z",
      "first_seen_at": "2026-05-31T06:21:59.231013Z",
      "last_seen_at": "2026-05-31T09:32:51.087280Z",
      "ai_is_related": true,
      "ai_score": 0.67,
      "ai_label": "ai_general",
      "ai_relevance_reason": "matched_ai_signal",
      "ai_signals": [],
      "ai_noise": [],
      "title_original": "中国汽车流通协会：5月中国汽车经销商库存预警指数为57.9%",
      "title_en": null,
      "title_zh": "中国汽车流通协会：5月中国汽车经销商库存预警指数为57.9%",
      "title_bilingual": "中国汽车流通协会：5月中国汽车经销商库存预警指数为57.9%"
    },
    {
      "id": "6649d6f533a1e60cd7b9e5e7a82605a1f895bc6f",
      "site_id": "opmlrss",
      "site_name": "OPML RSS",
      "source": "36氪 - AI",
      "title": "国家统计局：5月份，制造业采购经理指数（PMI）为50.0%",
      "url": "https://36kr.com/newsflashes/3832582533326471?f=rss",
      "published_at": "2026-05-31T02:24:33Z",
      "first_seen_at": "2026-05-31T06:21:59.231013Z",
      "last_seen_at": "2026-05-31T06:21:59.231013Z",
      "ai_is_related": true,
      "ai_score": 0.67,
      "ai_label": "ai_general",
      "ai_relevance_reason": "matched_ai_signal",
      "ai_signals": [],
      "ai_noise": [],
      "title_original": "国家统计局：5月份，制造业采购经理指数（PMI）为50.0%",
      "title_en": null,
      "title_zh": "国家统计局：5月份，制造业采购经理指数（PMI）为50.0%",
      "title_bilingual": "国家统计局：5月份，制造业采购经理指数（PMI）为50.0%"
    },
    {
      "id": "1fcb90f7cb992f02eafdd141dde0b230d8432d13",
      "site_id": "opmlrss",
      "site_name": "OPML RSS",
      "source": "36氪 - AI",
      "title": "天猫618：多品牌手机集体降价，iPhone降2500元，华为降3500元",
      "url": "https://36kr.com/newsflashes/3832582092252808?f=rss",
      "published_at": "2026-05-31T02:24:06Z",
      "first_seen_at": "2026-05-31T06:21:59.231013Z",
      "last_seen_at": "2026-05-31T06:21:59.231013Z",
      "ai_is_related": true,
      "ai_score": 0.65,
      "ai_label": "ai_general",
      "ai_relevance_reason": "matched_ai_signal",
      "ai_signals": [],
      "ai_noise": [
        "天猫"
      ],
      "title_original": "天猫618：多品牌手机集体降价，iPhone降2500元，华为降3500元",
      "title_en": null,
      "title_zh": "天猫618：多品牌手机集体降价，iPhone降2500元，华为降3500元",
      "title_bilingual": "天猫618：多品牌手机集体降价，iPhone降2500元，华为降3500元"
    },
    {
      "id": "92897588e6d0f0495e59b562470a3cee23decfbd",
      "site_id": "opmlrss",
      "site_name": "OPML RSS",
      "source": "36氪 - AI",
      "title": "预计减免关税近600万元，封关后首架“零关税”客机通关",
      "url": "https://36kr.com/newsflashes/3832506934388354?f=rss",
      "published_at": "2026-05-31T02:12:33Z",
      "first_seen_at": "2026-05-31T06:21:59.231013Z",
      "last_seen_at": "2026-05-31T06:21:59.231013Z",
      "ai_is_related": true,
      "ai_score": 0.67,
      "ai_label": "ai_general",
      "ai_relevance_reason": "matched_ai_signal",
      "ai_signals": [],
      "ai_noise": [],
      "title_original": "预计减免关税近600万元，封关后首架“零关税”客机通关",
      "title_en": null,
      "title_zh": "预计减免关税近600万元，封关后首架“零关税”客机通关",
      "title_bilingual": "预计减免关税近600万元，封关后首架“零关税”客机通关"
    },
    {
      "id": "f93e876de4705db3183aaa3d43f87f80209e8886",
      "site_id": "opmlrss",
      "site_name": "OPML RSS",
      "source": "36氪 - AI",
      "title": "智元机器人合伙人姚卯青：今年上半年智元海外收入占比已近20%",
      "url": "https://36kr.com/newsflashes/3832506045818500?f=rss",
      "published_at": "2026-05-31T01:58:39Z",
      "first_seen_at": "2026-05-31T06:21:59.231013Z",
      "last_seen_at": "2026-05-31T06:21:59.231013Z",
      "ai_is_related": true,
      "ai_score": 0.7,
      "ai_label": "robotics",
      "ai_relevance_reason": "matched_ai_signal",
      "ai_signals": [
        "机器人"
      ],
      "ai_noise": [],
      "title_original": "智元机器人合伙人姚卯青：今年上半年智元海外收入占比已近20%",
      "title_en": null,
      "title_zh": "智元机器人合伙人姚卯青：今年上半年智元海外收入占比已近20%",
      "title_bilingual": "智元机器人合伙人姚卯青：今年上半年智元海外收入占比已近20%"
    },
    {
      "id": "24f82e4d86f2d40930096ab96ee89257cf49f2a1",
      "site_id": "opmlrss",
      "site_name": "OPML RSS",
      "source": "36氪 - AI",
      "title": "欧洲央行管委佩雷拉：必须尽早应对通胀",
      "url": "https://36kr.com/newsflashes/3832504586577798?f=rss",
      "published_at": "2026-05-31T01:28:09Z",
      "first_seen_at": "2026-05-31T01:34:42.347252Z",
      "last_seen_at": "2026-05-31T06:21:59.231013Z",
      "ai_is_related": true,
      "ai_score": 0.67,
      "ai_label": "ai_general",
      "ai_relevance_reason": "matched_ai_signal",
      "ai_signals": [],
      "ai_noise": [],
      "title_original": "欧洲央行管委佩雷拉：必须尽早应对通胀",
      "title_en": null,
      "title_zh": "欧洲央行管委佩雷拉：必须尽早应对通胀",
      "title_bilingual": "欧洲央行管委佩雷拉：必须尽早应对通胀"
    },
    {
      "id": "c28bec3db1d49b936f08a671169fe0079b3f604e",
      "site_id": "opmlrss",
      "site_name": "OPML RSS",
      "source": "36氪 - AI",
      "title": "小米技术：MiMo-V2.5实现五大核心突破，降价后仍能实现收支平衡",
      "url": "https://36kr.com/newsflashes/3832525007284097?f=rss",
      "published_at": "2026-05-31T01:26:02Z",
      "first_seen_at": "2026-05-31T01:34:42.347252Z",
      "last_seen_at": "2026-05-31T06:21:59.231013Z",
      "ai_is_related": true,
      "ai_score": 0.7,
      "ai_label": "ai_tech",
      "ai_relevance_reason": "matched_ai_signal",
      "ai_signals": [
        "技术"
      ],
      "ai_noise": [],
      "title_original": "小米技术：MiMo-V2.5实现五大核心突破，降价后仍能实现收支平衡",
      "title_en": null,
      "title_zh": "小米技术：MiMo-V2.5实现五大核心突破，降价后仍能实现收支平衡",
      "title_bilingual": "小米技术：MiMo-V2.5实现五大核心突破，降价后仍能实现收支平衡"
    },
    {
      "id": "203fd3e3f8b8609df49cc1e8f59c91de57c6a7de",
      "site_id": "opmlrss",
      "site_name": "OPML RSS",
      "source": "36氪 - AI",
      "title": "丰田回应将中止雷克萨斯下一代纯电轿车开发",
      "url": "https://36kr.com/newsflashes/3832495904171908?f=rss",
      "published_at": "2026-05-31T01:15:06Z",
      "first_seen_at": "2026-05-31T01:34:42.347252Z",
      "last_seen_at": "2026-05-31T06:21:59.231013Z",
      "ai_is_related": true,
      "ai_score": 0.67,
      "ai_label": "ai_general",
      "ai_relevance_reason": "matched_ai_signal",
      "ai_signals": [],
      "ai_noise": [],
      "title_original": "丰田回应将中止雷克萨斯下一代纯电轿车开发",
      "title_en": null,
      "title_zh": "丰田回应将中止雷克萨斯下一代纯电轿车开发",
      "title_bilingual": "丰田回应将中止雷克萨斯下一代纯电轿车开发"
    },
    {
      "id": "f57fc5a0700296e99a45a4386670deeec4bd8f0f",
      "site_id": "opmlrss",
      "site_name": "OPML RSS",
      "source": "36氪 - AI",
      "title": "我国成功发射卫星互联网技术试验卫星",
      "url": "https://36kr.com/newsflashes/3832495203657606?f=rss",
      "published_at": "2026-05-31T00:55:43Z",
      "first_seen_at": "2026-05-31T01:34:42.347252Z",
      "last_seen_at": "2026-05-31T06:21:59.231013Z",
      "ai_is_related": true,
      "ai_score": 0.7,
      "ai_label": "ai_tech",
      "ai_relevance_reason": "matched_ai_signal",
      "ai_signals": [
        "技术"
      ],
      "ai_noise": [],
      "title_original": "我国成功发射卫星互联网技术试验卫星",
      "title_en": null,
      "title_zh": "我国成功发射卫星互联网技术试验卫星",
      "title_bilingual": "我国成功发射卫星互联网技术试验卫星"
    },
    {
      "id": "58df2b85c3dbbcf5621be08d742aa4ee12061e8e",
      "site_id": "opmlrss",
      "site_name": "OPML RSS",
      "source": "ReadHub",
      "title": "软银承诺斥资 750 亿欧元在法国建设人工智能设施",
      "url": "https://readhub.cn/topic/8tYwZwF7BvS",
      "published_at": "2026-05-30T20:54:56Z",
      "first_seen_at": "2026-05-30T21:34:07.181560Z",
      "last_seen_at": "2026-05-31T13:49:50.572130Z",
      "ai_is_related": true,
      "ai_score": 0.71,
      "ai_label": "ai_general",
      "ai_relevance_reason": "matched_ai_signal",
      "ai_signals": [
        "人工智能"
      ],
      "ai_noise": [],
      "title_original": "软银承诺斥资 750 亿欧元在法国建设人工智能设施",
      "title_en": null,
      "title_zh": "软银承诺斥资 750 亿欧元在法国建设人工智能设施",
      "title_bilingual": "软银承诺斥资 750 亿欧元在法国建设人工智能设施"
    }
  ],
  "all_mode_data_url": "data/latest-24h-all.json"
}